feather_extract/__init__.py
feather_extract/excel_writer.py
feather_extract/extract_text.py
feather_extract/format_text.py
feather_extract/forms.py
feather_extract/utils.py
feather_extract/data/standard-form-filled-out.pdf
feather_extract/data/standard_form.pdf
feather_extract-0.1.16.dist-info/METADATA
feather_extract-0.1.16.dist-info/WHEEL
feather_extract-0.1.16.dist-info/top_level.txt
feather_extract-0.1.16.dist-info/RECORD
