Metadata-Version: 2.1
Name: feather_extract
Version: 0.1.16
Summary: A package for extracting handwritten data from PDF documents, and returning an Excel workbook output.
Home-page: https://www.featherdata.io/
Author: Jonathan Hofmann
Author-email: Jonathan Hofmann <awsjonathan99@gmail.com>
License: MIT
Project-URL: Homepage, https://www.featherdata.io/
Classifier: Programming Language :: Python :: 3
Classifier: License :: OSI Approved :: MIT License
Classifier: Operating System :: OS Independent
Requires-Python: >=3.8
Requires-Dist: azure-ai-formrecognizer ==3.3.3
Requires-Dist: openpyxl ==3.1.2
